{
  "health": 33.333333333333336,
  "hunger": 100,
  "happiness": 0.0,
  "energy": 0,
  "level": 3,
  "streak": 7,
  "total_commits": 240,
  "mood": "exhausted",
  "rpg_stats": {},
  "achievements": [
    "\ud83e\uddd9\u200d\u2642\ufe0f Elder Council",
    "\ud83d\udc51 Social Elite",
    "\ud83d\udc8e Quality Craftsman"
  ],
  "history": [
    {
      "timestamp": "2026-02-24T21:49:49.985313+00:00",
      "daily_commits": 23,
      "daily_prs": 0,
      "health": 50,
      "mood": "neutral",
      "streak": 0,
      "tier": "elder"
    },
    {
      "timestamp": "2026-02-25T07:09:50.509038+00:00",
      "daily_commits": 5,
      "daily_prs": 0,
      "health": 34.45666666666667,
      "mood": "exhausted",
      "streak": 1,
      "tier": "elder"
    },
    {
      "timestamp": "2026-02-26T07:08:10.200686+00:00",
      "daily_commits": 0,
      "daily_prs": 0,
      "health": 27.48,
      "mood": "struggling",
      "streak": 2,
      "tier": "elder"
    },
    {
      "timestamp": "2026-02-27T07:02:39.147951+00:00",
      "daily_commits": 1,
      "daily_prs": 0,
      "health": 24.92,
      "mood": "struggling",
      "streak": 1,
      "tier": "elder"
    },
    {
      "timestamp": "2026-02-28T06:49:14.751514+00:00",
      "daily_commits": 0,
      "daily_prs": 0,
      "health": 16.97666666666667,
      "mood": "struggling",
      "streak": 2,
      "tier": "elder"
    },
    {
      "timestamp": "2026-03-01T06:55:07.068183+00:00",
      "daily_commits": 0,
      "daily_prs": 0,
      "health": 17.750000000000004,
      "mood": "struggling",
      "streak": 1,
      "tier": "elder"
    },
    {
      "timestamp": "2026-03-02T07:06:40.741538+00:00",
      "daily_commits": 0,
      "daily_prs": 0,
      "health": 22.27333333333333,
      "mood": "struggling",
      "streak": 0,
      "tier": "elder"
    },
    {
      "timestamp": "2026-03-03T07:01:13.104509+00:00",
      "daily_commits": 0,
      "daily_prs": 0,
      "health": 28.939999999999998,
      "mood": "struggling",
      "streak": 0,
      "tier": "elder"
    },
    {
      "timestamp": "2026-03-03T15:35:48.138692+00:00",
      "daily_commits": 13,
      "daily_prs": 0,
      "health": 34.77333333333333,
      "mood": "elite",
      "streak": 0,
      "tier": "elder"
    },
    {
      "timestamp": "2026-03-03T21:31:26.179639+00:00",
      "daily_commits": 29,
      "daily_prs": 0,
      "health": 30.871666666666666,
      "mood": "elite",
      "streak": 1,
      "tier": "elder"
    },
    {
      "timestamp": "2026-03-03T21:34:39.806015+00:00",
      "daily_commits": 30,
      "daily_prs": 0,
      "health": 14.89,
      "mood": "struggling",
      "streak": 2,
      "tier": "elder"
    },
    {
      "timestamp": "2026-03-03T21:40:35.373644+00:00",
      "daily_commits": 31,
      "daily_prs": 0,
      "health": 20.82166666666667,
      "mood": "struggling",
      "streak": 3,
      "tier": "elder"
    },
    {
      "timestamp": "2026-03-03T21:58:40.188109+00:00",
      "daily_commits": 35,
      "daily_prs": 0,
      "health": 28.8475,
      "mood": "struggling",
      "streak": 4,
      "tier": "elder"
    },
    {
      "timestamp": "2026-03-03T22:06:51.487133+00:00",
      "daily_commits": 36,
      "daily_prs": 0,
      "health": 33.333333333333336,
      "mood": "exhausted",
      "streak": 5,
      "tier": "elder"
    },
    {
      "timestamp": "2026-03-03T22:12:21.781275+00:00",
      "daily_commits": 37,
      "daily_prs": 0,
      "health": 33.333333333333336,
      "mood": "exhausted",
      "streak": 6,
      "tier": "elder"
    }
  ],
  "brutal_stats": {
    "tier": "elder",
    "github_years": 9.998631074606434,
    "social_score": 1.25,
    "social_penalties": [
      "quality_curator"
    ],
    "avg_repo_quality": 0.8304687500000009,
    "commit_quality_score": 0.95,
    "commit_quality_penalties": [
      "no_description"
    ],
    "multipliers": {
      "xp": 0.25,
      "decay": 0.8,
      "requirements": 4.0
    },
    "total_stars": 605,
    "language_diversity_penalty": 0.9,
    "xp_earned": 103.545,
    "dominant_language": "Python",
    "issues_closed": 4,
    "issue_close_ratio": 0.6666666666666666,
    "issue_score": 1.2,
    "can_prestige": false,
    "prestige_missing": [
      "Need Level 10"
    ]
  },
  "last_update": "2026-03-03T22:12:21.781275+00:00"
}